CodeCommitListCommits/__init__.py
CodeCommitListCommits/list_commits.py
CodeCommit_ListCommits-1.0.2.dist-info/LICENSE.txt
CodeCommit_ListCommits-1.0.2.dist-info/METADATA
CodeCommit_ListCommits-1.0.2.dist-info/WHEEL
CodeCommit_ListCommits-1.0.2.dist-info/top_level.txt
CodeCommit_ListCommits-1.0.2.dist-info/RECORD
