Metadata-Version: 2.1
Name: CodeCommit-ListCommits
Version: 1.0.2
Summary: Retrieve all commits from an AWS CodeCommit repository in bulk
Author-email: tra <tisk0711ngm@gmail.com>
Maintainer-email: tra <tisk0711ngm@gmail.com>
License: MIT License
Project-URL: Source, https://github.com/clcl777/CodeCommit-ListCommits
Classifier: Development Status :: 5 - Production/Stable
Classifier: Intended Audience :: Developers
Classifier: Programming Language :: Python :: 3
Classifier: Environment :: Web Environment
Classifier: License :: OSI Approved :: MIT License
Classifier: Operating System :: OS Independent
Classifier: Typing :: Typed
Classifier: Topic :: Software Development
Requires-Python: >=3.8
License-File: LICENSE.txt
Requires-Dist: dulwich >=0.22.1
